hiresprv/__init__.py
hiresprv/archive.py
hiresprv/auth.py
hiresprv/database.py
hiresprv/download.py
hiresprv/idldriver.py
hiresprv/status.py
sphinx/__init__.py
sphinx/conf.py
hiresprv-3.0.5.dist-info/METADATA
hiresprv-3.0.5.dist-info/WHEEL
hiresprv-3.0.5.dist-info/top_level.txt
hiresprv-3.0.5.dist-info/RECORD
